sshpubkeys/__init__.py
sshpubkeys/exceptions.py
sshpubkeys/keys.py
py3sshpubkeys-3.4.0.dist-info/LICENSE.txt
py3sshpubkeys-3.4.0.dist-info/METADATA
py3sshpubkeys-3.4.0.dist-info/WHEEL
py3sshpubkeys-3.4.0.dist-info/top_level.txt
py3sshpubkeys-3.4.0.dist-info/RECORD
