Metadata-Version: 2.2
Name: py3sshpubkeys
Version: 3.4.0
Summary: SSH public key parser
Home-page: https://github.com/ojarva/python-sshpubkeys
Author: Olli Jarva
Author-email: olli@jarva.fi
License: BSD
Keywords: ssh pubkey public key openssh ssh-rsa ssh-dss ssh-ed25519
Classifier: Development Status :: 4 - Beta
Classifier: Intended Audience :: Developers
Classifier: Intended Audience :: System Administrators
Classifier: Topic :: Security
Classifier: License :: OSI Approved :: BSD License
Classifier: Programming Language :: Python :: 3
Classifier: Programming Language :: Python :: 3.9
Classifier: Programming Language :: Python :: 3.10
Classifier: Programming Language :: Python :: 3.11
Classifier: Programming Language :: Python :: Implementation :: PyPy
Requires-Python: >=3
License-File: LICENSE.txt
Requires-Dist: cryptography==43.0.0
Provides-Extra: dev
Requires-Dist: twine; extra == "dev"
Requires-Dist: wheel; extra == "dev"
Requires-Dist: yapf; extra == "dev"
Dynamic: author
Dynamic: author-email
Dynamic: classifier
Dynamic: description
Dynamic: home-page
Dynamic: keywords
Dynamic: license
Dynamic: provides-extra
Dynamic: requires-dist
Dynamic: requires-python
Dynamic: summary
